urllib3_ext_hface/__init__.py
urllib3_ext_hface/_configuration.py
urllib3_ext_hface/_error_codes.py
urllib3_ext_hface/_typing.py
urllib3_ext_hface/_version.py
urllib3_ext_hface/py.typed
urllib3_ext_hface/events/__init__.py
urllib3_ext_hface/events/_events.py
urllib3_ext_hface/protocols/__init__.py
urllib3_ext_hface/protocols/_factories.py
urllib3_ext_hface/protocols/_protocols.py
urllib3_ext_hface/protocols/http1/__init__.py
urllib3_ext_hface/protocols/http1/_h11.py
urllib3_ext_hface/protocols/http1/_helpers.py
urllib3_ext_hface/protocols/http2/__init__.py
urllib3_ext_hface/protocols/http2/_h2.py
urllib3_ext_hface/protocols/http3/__init__.py
urllib3_ext_hface/protocols/http3/_aioquic.py
urllib3_ext_hface-0.3.4.dist-info/METADATA
urllib3_ext_hface-0.3.4.dist-info/WHEEL
urllib3_ext_hface-0.3.4.dist-info/licenses/AUTHORS
urllib3_ext_hface-0.3.4.dist-info/licenses/LICENSE
urllib3_ext_hface-0.3.4.dist-info/licenses/NOTICE
urllib3_ext_hface-0.3.4.dist-info/RECORD
