Metadata-Version: 2.1
Name: urllib3-ext-hface
Version: 0.3.4
Summary: urllib3 extension to support HTTP/1.1, HTTP/2 and HTTP/3 independently of Python httplib
Project-URL: Changelog, https://github.com/Ousret/urllib3-ext-hface/blob/main/CHANGELOG.rst
Project-URL: Documentation, https://urllib3.readthedocs.io
Project-URL: Code, https://github.com/Ousret/urllib3-ext-hface
Project-URL: Issue tracker, https://github.com/Ousret/urllib3-ext-hface/issues
Author-email: Miloslav Pojman <mpojman@akamai.com>
Maintainer-email: "Ahmed R. TAHRI" <ahmed.tahri@cloudnursery.dev>
License: Apache-2.0
License-File: AUTHORS
License-File: LICENSE
License-File: NOTICE
Keywords: extension,h11,h2,h3,quic,urllib3
Classifier: Development Status :: 4 - Beta
Classifier: Environment :: Web Environment
Classifier: Intended Audience :: Developers
Classifier: License :: OSI Approved :: Apache Software License
Classifier: Operating System :: OS Independent
Classifier: Programming Language :: Python
Classifier: Programming Language :: Python :: 3
Classifier: Programming Language :: Python :: 3 :: Only
Classifier: Programming Language :: Python :: 3.7
Classifier: Programming Language :: Python :: 3.8
Classifier: Programming Language :: Python :: 3.9
Classifier: Programming Language :: Python :: 3.10
Classifier: Programming Language :: Python :: 3.11
Classifier: Programming Language :: Python :: 3.12
Classifier: Programming Language :: Python :: Implementation :: CPython
Classifier: Programming Language :: Python :: Implementation :: PyPy
Classifier: Topic :: Internet :: WWW/HTTP
Classifier: Topic :: Software Development :: Libraries
Classifier: Typing :: Typed
Requires-Python: >=3.7
Requires-Dist: h11<1.0.0,>=0.11.0
Requires-Dist: h2<5.0.0,>=4.0.0
Requires-Dist: qh3<1.0.0,>=0.10.0
